json_encode_manager.py
json_encode_manager-0.0.2.dist-info/DESCRIPTION.rst
json_encode_manager-0.0.2.dist-info/METADATA
json_encode_manager-0.0.2.dist-info/RECORD
json_encode_manager-0.0.2.dist-info/WHEEL
json_encode_manager-0.0.2.dist-info/metadata.json
json_encode_manager-0.0.2.dist-info/top_level.txt
