Metadata-Version: 2.0
Name: json-encode-manager
Version: 0.0.2
Summary: JSON encode helper
Home-page: https://github.com/anjianshi/json_encode_manager
Author: anjianshi
Author-email: anjianshi@gmail.com
License: MIT
Platform: UNKNOWN
Classifier: Intended Audience :: Developers
Classifier: License :: OSI Approved :: MIT License
Classifier: Operating System :: OS Independent
Classifier: Programming Language :: Python
Classifier: Programming Language :: Python :: 3
